{"session_id": "20250909-030143", "started_at": "2025-09-08T17:01:43.892346Z", "chunks": [{"world_state_updates": [{"location": "Forest", "update": "The team is searching for a wolf."}], "character_events": [], "quest_updates": [{"quest": "Find the Wolf", "update": "The team is actively searching."}]}, {"world_state_updates": [{"location": "Forest", "update": "The team is searching for a wolf."}], "character_events": [], "quest_updates": [{"quest": "Find the Wolf", "update": "The team is actively searching."}]}, {"world_state_updates": [{"location": "Forest", "update": "The team is searching for a wolf."}], "character_events": [], "quest_updates": [{"quest": "Find the Wolf", "update": "The team is actively searching."}]}, {"world_state_updates": [{"location": "Forest", "update": "The team is searching for a wolf."}], "character_events": [], "quest_updates": [{"quest": "Find the Wolf", "update": "The team is actively searching."}]}]}